instamatte/__init__.py
instamatte/__main__.py
instamatte/cli.py
instamatte/configuration.py
instamatte/file_operations.py
instamatte/image_processing.py
instamatte-0.4.0.dist-info/METADATA
instamatte-0.4.0.dist-info/WHEEL
instamatte-0.4.0.dist-info/entry_points.txt
instamatte-0.4.0.dist-info/licenses/LICENSE
instamatte-0.4.0.dist-info/RECORD
