Metadata-Version: 2.4
Name: instamatte
Version: 0.4.0
Summary: Multi-format image processor for social media
Author-email: Arthur Ryzhak <ryzhakar@gmail.com>
License-File: LICENSE
Requires-Python: >=3.9
Requires-Dist: pillow>=10.0.0
Requires-Dist: pydantic>=2.0.0
Requires-Dist: pyyaml>=6.0.0
Requires-Dist: rich>=13.0.0
Requires-Dist: typer>=0.9.0
